emocodes/__init__.py
emocodes/analysis/__init__.py
emocodes/analysis/codes.py
emocodes/analysis/coding.py
emocodes/analysis/features.py
emocodes/plotting/__init__.py
emocodes/plotting/analysis.py
emocodes/plotting/codes.py
emocodes/plotting/codes_plot.py
emocodes/plotting/summary.py
emocodes/processing/__init__.py
emocodes/processing/code.py
emocodes/processing/codes.py
emocodes/processing/video.py
emocodes-1.0.14.dist-info/LICENSE
emocodes-1.0.14.dist-info/METADATA
emocodes-1.0.14.dist-info/WHEEL
emocodes-1.0.14.dist-info/top_level.txt
emocodes-1.0.14.dist-info/RECORD
